pylegifrance/__init__.py
pylegifrance/auth.py
pylegifrance/client.py
pylegifrance/config.py
pylegifrance/utils.py
pylegifrance/fonds/__init__.py
pylegifrance/fonds/code.py
pylegifrance/fonds/juri.py
pylegifrance/fonds/loda.py
pylegifrance/models/__init__.py
pylegifrance/models/base.py
pylegifrance/models/constants.py
pylegifrance/models/identifier.py
pylegifrance/models/code/__init__.py
pylegifrance/models/code/consult.py
pylegifrance/models/code/enum.py
pylegifrance/models/code/models.py
pylegifrance/models/code/search.py
pylegifrance/models/generated/model.py
pylegifrance/models/juri/__init__.py
pylegifrance/models/juri/api_wrappers.py
pylegifrance/models/juri/constants.py
pylegifrance/models/juri/filters.py
pylegifrance/models/juri/models.py
pylegifrance/models/juri/search.py
pylegifrance/models/loda/__init__.py
pylegifrance/models/loda/api_wrappers.py
pylegifrance/models/loda/constants.py
pylegifrance/models/loda/models.py
pylegifrance/models/loda/search.py
pylegifrance-1.2.1b3.dist-info/licenses/LICENSE
pylegifrance-1.2.1b3.dist-info/METADATA
pylegifrance-1.2.1b3.dist-info/WHEEL
pylegifrance-1.2.1b3.dist-info/top_level.txt
pylegifrance-1.2.1b3.dist-info/RECORD
