Metadata-Version: 2.4
Name: pylegifrance
Version: 1.2.1b3
Summary: Librairie qui fournit des fonctions simples pour rechercher dans legifrance
Author-email: Raphaël d'Assignies <rdassignies@protonmail.ch>, "Frederic F." <17061560+freddo1503@users.noreply.github.com>
License-Expression: MIT
Project-URL: Homepage, https://github.com/pylegifrance/pylegifrance
Classifier: Programming Language :: Python :: 3.12
Classifier: Operating System :: OS Independent
Requires-Python: >=3.12
License-File: LICENSE
Requires-Dist: dotenv>=0.9.9
Requires-Dist: tenacity>=9.0.0
Requires-Dist: pydantic>=2.10.6
Requires-Dist: requests>=2.32.3
Provides-Extra: docs
Requires-Dist: mkdocs>=1.6.1; extra == "docs"
Requires-Dist: mkdocs-awesome-autolinks>=1.0.0; extra == "docs"
Requires-Dist: mkdocs-awesome-pages-plugin>=2.10.1; extra == "docs"
Requires-Dist: mkdocs-material>=9.6.14; extra == "docs"
Requires-Dist: mkdocs-mermaid2-plugin>=1.2.1; extra == "docs"
Requires-Dist: mkdocs-minify-plugin>=0.8.0; extra == "docs"
Requires-Dist: plantuml-markdown>=3.11.1; extra == "docs"
Requires-Dist: pymdown-extensions>=10.15; extra == "docs"
Dynamic: license-file
